{"version":"0.4","title":"Mycart","type":"page","content":[{"id":"38016ca1","settings":{"content_position":"middle"},"elements":[{"id":"6f4562e1","settings":{"_column_size":100},"elements":[{"id":"6c4ed8a2","settings":{"editor":"<!-- wp:cover {\"url\":\"https:\/\/rm8.299.myftpupload.comwp-content\/uploads\/2021\/01\/other-small-3.jpg\",\"id\":143,\"dimRatio\":0} -->\n<div class=\"wp-block-cover\" style=\"background-image: url('https:\/\/rm8.299.myftpupload.comwp-content\/uploads\/2021\/01\/other-small-3.jpg');\">\n<div class=\"wp-block-cover__inner-container\">\n<h1 class=\"has-text-align-center has-large-font-size\">Welcome to Mycart official website!<\/h1>\n<p class=\"has-text-align-center has-white-color has-text-color has-large-font-size\"><!-- \/wp:paragraph --><!-- wp:paragraph {\"align\":\"center\",\"textColor\":\"white\"} --><\/p>\n<p>Apply coupon code MYCART to get discount of 10% at checkout. Valid once per user.<\/p>\n<p>We'll be starting our service <strong>soon!<\/strong> Stay connected with us to know more. Hurry up!\u00a0<\/p>\n<p class=\"has-text-align-center has-white-color has-text-color\"><!-- \/wp:paragraph --><!-- wp:button {\"align\":\"center\"} --><\/p>\n<p class=\"wp-block-button aligncenter\"><strong><a class=\"wp-block-button__link\" href=\"https:\/\/rm8.299.myftpupload.comshop\/\">Wishlist now!<\/a><\/strong><\/p>\n<!-- wp:paragraph {\"align\":\"center\",\"placeholder\":\"Write title\u2026\",\"textColor\":\"white\",\"fontSize\":\"large\"} --><\/div>\n<\/div>\n<!-- \/wp:media-text --><!-- wp:woocommerce\/featured-product \/-->","_background_hover_transition":{"unit":"px","size":0.90000000000000002220446049250313080847263336181640625,"sizes":[]},"align":"center","text_color":"#404A1CF5","_animation":"slideInUp","animation_duration":"slow","_background_background":"classic","_background_color":"#396C37CC","_background_color_stop":{"unit":"%","size":34,"sizes":[]},"_background_color_b":"#F229294D","_background_position":"center center","_background_repeat":"no-repeat","_background_size":"cover","__globals__":{"typography_typography":"globals\/typography?id=primary"}},"elements":[],"isInner":false,"widgetType":"text-editor","elType":"widget"}],"isInner":false,"elType":"column"}],"isInner":false,"elType":"section"},{"id":"1211fd3e","settings":{"animation":"slideInRight"},"elements":[{"id":"34d98c7b","settings":{"_column_size":100,"_inline_size":null},"elements":[{"id":"2403c93c","settings":{"title":"Product Categories","header_size":"h3","align":"center"},"elements":[],"isInner":false,"widgetType":"heading","elType":"widget"},{"id":"a291c07","settings":{"count_before_text":"(","count_after_text":")","desc_after_text":"...","show_count":"","columns":"6","number":6,"hide_default_cat":"yes","thumb_size":"woocommerce_gallery_thumbnail","carousel_enabled":"yes","slides_to_scroll":"2"},"elements":[],"isInner":false,"widgetType":"woo-products-widgets-categories","elType":"widget"}],"isInner":false,"elType":"column"}],"isInner":false,"elType":"section"},{"id":"2eb3ba5c","settings":{"custom_height":{"unit":"px","size":288,"sizes":[]},"animation":"slideInUp","animation_duration":"slow","__globals__":{"shape_divider_top_color":"globals\/colors?id=primary"}},"elements":[{"id":"109e8e6b","settings":{"_column_size":100,"_inline_size":null},"elements":[{"id":"3c4cc239","settings":{"title":"Latest Products","header_size":"h3","align":"center"},"elements":[],"isInner":false,"widgetType":"heading","elType":"widget"},{"id":"2b75b23c","settings":{"presets":"preset-5","columns":"4","number":4,"products_order":"title","sale_badge_text":"Special Price!","equal_height_cols":"true","thumb_size":"shop_thumbnail"},"elements":[],"isInner":false,"widgetType":"woo-products-widgets-products","elType":"widget"}],"isInner":false,"elType":"column"}],"isInner":false,"elType":"section"}]}